livia/__init__.py
livia/application.py
livia/chat.py
livia-0.1.4.dist-info/METADATA
livia-0.1.4.dist-info/WHEEL
livia-0.1.4.dist-info/RECORD
